examples/__init__.py
examples/in_memory/__init__.py
examples/in_memory/main.py
examples/redis/__init__.py
examples/redis/index.html
examples/redis/main.py
starlette_cache-0.1.3.dist-info/METADATA
starlette_cache-0.1.3.dist-info/WHEEL
starlette_cache/__init__.py
starlette_cache/backends/__init__.py
starlette_cache/coder.py
starlette_cache/decorator.py
starlette_cache/key_builder.py
starlette_cache/py.typed
starlette_cache-0.1.3.dist-info/RECORD
