Metadata-Version: 2.1
Name: starlette-cache
Version: 0.1.3
Summary: Cache for Starlette
Home-page: https://github.com/lesleslie/starlette-cache
Author-Email: lesleslie <les@wedgwoodwebworks.com>
License: BSD-3-Clause
Project-URL: Homepage, https://github.com/lesleslie/starlette-cache
Project-URL: Documentation, https://github.com/lesleslie/starlette-cache
Project-URL: Repository, https://github.com/lesleslie/starlette-cache
Requires-Python: >=3.11
Requires-Dist: starlette>=0.26.1
Requires-Dist: uvicorn>=0.21.1
Requires-Dist: redis>=4.5.4
Requires-Dist: aiomcache>=0.8.1
Requires-Dist: pendulum>=2.1.2
Requires-Dist: aiohttp>=3.8.4
Requires-Dist: typing-extensions>=4.5.0
Requires-Dist: msgspec>=0.14.1
Requires-Dist: acb>=0.1.4
Requires-Dist: starlette-async-jinja>=0.1.1
Requires-Dist: cashews>=6.0.2
